theo_eco_simulator/__init__.py
theo_eco_simulator/community.py
theo_eco_simulator/integration.py
theo_eco_simulator/models.py
theo_eco_simulator-0.0.6.dist-info/LICENSE
theo_eco_simulator-0.0.6.dist-info/METADATA
theo_eco_simulator-0.0.6.dist-info/WHEEL
theo_eco_simulator-0.0.6.dist-info/top_level.txt
theo_eco_simulator-0.0.6.dist-info/RECORD
