Metadata-Version: 2.1
Name: theo-eco-simulator
Version: 0.0.6
Summary: A collection of mathematical models in ecology, and tools to efficiently solve them, and manipulate their outputs.
Home-page: https://github.com/pablolich/theo_eco_simulator
Author: Pablo Lechon-Alonso
Author-email: plechon@uchicago.edu
License: UNKNOWN
Platform: UNKNOWN
Classifier: Programming Language :: Python :: 3
Classifier: License :: OSI Approved :: MIT License
Classifier: Operating System :: OS Independent
Requires-Python: >=3.6
License-File: LICENSE
